jb_utils/__init__.py
jb_utils/diff_match_patch.py
jb_utils/diffsidebyside.py
tags2myst/__init__.py
tags2myst/cli.py
tags2myst/empinken2myst.py
tags2myst/tagstyler2myst.py
ou_jupyter_book_tools-0.0.4.dist-info/LICENSE
ou_jupyter_book_tools-0.0.4.dist-info/METADATA
ou_jupyter_book_tools-0.0.4.dist-info/WHEEL
ou_jupyter_book_tools-0.0.4.dist-info/entry_points.txt
ou_jupyter_book_tools-0.0.4.dist-info/top_level.txt
ou_jupyter_book_tools-0.0.4.dist-info/RECORD
