Metadata-Version: 2.1
Name: ou-jupyter-book-tools
Version: 0.0.4
Summary: Tools for working with Jupyter books.
Home-page: UNKNOWN
Author: Tony Hirst
Author-email: tony.hirst@gmail.com
License: UNKNOWN
Platform: UNKNOWN
License-File: LICENSE
Requires-Dist: click
Requires-Dist: nbformat
